dash_canvas/AlternativeCanvas.py
dash_canvas/DashCanvas.py
dash_canvas/__init__.py
dash_canvas/_imports_.py
dash_canvas/dash_canvas.dev.js
dash_canvas/dash_canvas.min.js
dash_canvas/metadata.json
dash_canvas/package.json
dash_canvas/components/__init__.py
dash_canvas/components/_components.py
dash_canvas/test/__init__.py
dash_canvas/test/test_image_processing_utils.py
dash_canvas/test/test_parse_json.py
dash_canvas/test/test_registration.py
dash_canvas/utils/__init__.py
dash_canvas/utils/exposure.py
dash_canvas/utils/image_processing_utils.py
dash_canvas/utils/io_utils.py
dash_canvas/utils/parse_json.py
dash_canvas/utils/plot_utils.py
dash_canvas/utils/registration.py
tests/__init__.py
tests/test_usage.py
dash_canvas-0.0.11.dist-info/LICENSE
dash_canvas-0.0.11.dist-info/METADATA
dash_canvas-0.0.11.dist-info/WHEEL
dash_canvas-0.0.11.dist-info/top_level.txt
dash_canvas-0.0.11.dist-info/RECORD
