Metadata-Version: 1.0
Name: dash-canvas
Version: 0.0.11
Summary: Sketching pad for dash based on react-sketch
Home-page: https://github.com/plotly/dash-canvas
Author: Emmanuelle Gouillart emmanuelle.gouillart@nsup.org
Author-email: UNKNOWN
License: MIT
Platform: UNKNOWN
